<TextObjectProperties>
  <Layout>
    <Frame>
      <BorderWidth>0</BorderWidth>
      <BorderEffect>FLAT</BorderEffect>
      <Color>
        <Mode>COLORAREA_SOLID</Mode>
        <Luminosity>85</Luminosity>
        <FillDirection>COLORAREA_HORZ</FillDirection>
        <FillPattern>COLORAREA_PATTERN1</FillPattern>
        <PrimaryCol>
          <Col>
            <Red>4</Red>
            <Green>108</Green>
            <Blue>193</Blue>
            <Alpha>255</Alpha>
          </Col>
          <IsCalculated>false</IsCalculated>
          <ColorExpr></ColorExpr>
        </PrimaryCol>
        <SecondaryCol></SecondaryCol>
        <Alpha>255</Alpha>
      </Color>
      <Font></Font>
      <CaptionFont>
        <FontName>Tahoma</FontName>
        <PointSize1000>10000</PointSize1000>
        <Underline>false</Underline>
        <Bold>true</Bold>
        <Italic>false</Italic>
        <DropShadow>false</DropShadow>
      </CaptionFont>
      <Name></Name>
      <Bmp enctype="base64"></Bmp>
      <BmpMode>0</BmpMode>
      <Detached>false</Detached>
      <AllowMinimize>false</AllowMinimize>
      <AutoMinimize>false</AutoMinimize>
      <AllowMaximize>false</AllowMaximize>
      <AllowInfo>false</AllowInfo>
      <PrintIcon>false</PrintIcon>
      <CopyIcon>false</CopyIcon>
      <XLIcon>false</XLIcon>
      <SearchIcon>false</SearchIcon>
      <SelectPossibleIcon>false</SelectPossibleIcon>
      <SelectExcludedIcon>false</SelectExcludedIcon>
      <SelectAllIcon>false</SelectAllIcon>
      <ClearIcon>false</ClearIcon>
      <ClearOtherIcon>false</ClearOtherIcon>
      <LockIcon>false</LockIcon>
      <HelpText></HelpText>
      <ObjectId></ObjectId>
      <ShrinkFrameToData>true</ShrinkFrameToData>
      <ShowCaption>false</ShowCaption>
      <MultiLine>0</MultiLine>
      <ActiveBgColor>
        <Mode>COLORAREA_SOLID</Mode>
        <Luminosity>85</Luminosity>
        <FillDirection>COLORAREA_HORZ</FillDirection>
        <FillPattern>COLORAREA_PATTERN1</FillPattern>
        <PrimaryCol>
          <Col>
            <Red>210</Red>
            <Green>210</Green>
            <Blue>210</Blue>
            <Alpha>255</Alpha>
          </Col>
          <IsCalculated>false</IsCalculated>
          <ColorExpr></ColorExpr>
        </PrimaryCol>
        <SecondaryCol>
          <Col>
            <Red>153</Red>
            <Green>153</Green>
            <Blue>153</Blue>
            <Alpha>255</Alpha>
          </Col>
          <IsCalculated>false</IsCalculated>
          <ColorExpr></ColorExpr>
        </SecondaryCol>
        <Alpha>255</Alpha>
      </ActiveBgColor>
      <BgColor>
        <Mode>COLORAREA_SOLID</Mode>
        <Luminosity>85</Luminosity>
        <FillDirection>COLORAREA_HORZ</FillDirection>
        <FillPattern>COLORAREA_PATTERN1</FillPattern>
        <PrimaryCol>
          <Col>
            <Red>232</Red>
            <Green>232</Green>
            <Blue>232</Blue>
            <Alpha>255</Alpha>
          </Col>
          <IsCalculated>false</IsCalculated>
          <ColorExpr></ColorExpr>
        </PrimaryCol>
        <SecondaryCol>
          <Col>
            <Red>200</Red>
            <Green>200</Green>
            <Blue>200</Blue>
            <Alpha>255</Alpha>
          </Col>
          <IsCalculated>false</IsCalculated>
          <ColorExpr></ColorExpr>
        </SecondaryCol>
        <Alpha>255</Alpha>
      </BgColor>
      <ActiveFgColor>
        <Mode>COLORAREA_SOLID</Mode>
        <Luminosity>85</Luminosity>
        <FillDirection>COLORAREA_HORZ</FillDirection>
        <FillPattern>COLORAREA_PATTERN1</FillPattern>
        <PrimaryCol>
          <Col>
            <Red>54</Red>
            <Green>54</Green>
            <Blue>54</Blue>
            <Alpha>255</Alpha>
          </Col>
          <IsCalculated>false</IsCalculated>
          <ColorExpr></ColorExpr>
        </PrimaryCol>
        <SecondaryCol></SecondaryCol>
        <Alpha>255</Alpha>
      </ActiveFgColor>
      <FgColor>
        <Mode>COLORAREA_SOLID</Mode>
        <Luminosity>85</Luminosity>
        <FillDirection>COLORAREA_HORZ</FillDirection>
        <FillPattern>COLORAREA_PATTERN1</FillPattern>
        <PrimaryCol>
          <Col>
            <Red>54</Red>
            <Green>54</Green>
            <Blue>54</Blue>
            <Alpha>255</Alpha>
          </Col>
          <IsCalculated>false</IsCalculated>
          <ColorExpr></ColorExpr>
        </PrimaryCol>
        <SecondaryCol></SecondaryCol>
        <Alpha>255</Alpha>
      </FgColor>
      <FixCorner>true</FixCorner>
      <FixCornerSize>21</FixCornerSize>
      <RelCornerSize>4059000000000000</RelCornerSize>
      <Power>4000000000000000</Power>
      <RoundedShape>true</RoundedShape>
      <EnableTopLeftRounded>true</EnableTopLeftRounded>
      <EnableTopRightRounded>true</EnableTopRightRounded>
      <EnableBottomLeftRounded>true</EnableBottomLeftRounded>
      <EnableBottomRightRounded>true</EnableBottomRightRounded>
      <Light>3FEE666666666666</Light>
      <Dark>3FC3333333333333</Dark>
      <Rainbow>false</Rainbow>
      <TextAdjustHorizontal>0</TextAdjustHorizontal>
      <TextAdjustVertical>4</TextAdjustVertical>
      <Show></Show>
      <AllowMoveSize>true</AllowMoveSize>
      <AllowCopyClone>true</AllowCopyClone>
      <dummy></dummy>
      <CustomObjectGuid enctype="base64"></CustomObjectGuid>
      <CustomObjectProperties enctype="base64"></CustomObjectProperties>
      <ScrollBkgColor>
        <Col>
          <Red>255</Red>
          <Green>255</Green>
          <Blue>255</Blue>
          <Alpha>255</Alpha>
        </Col>
        <IsCalculated>false</IsCalculated>
        <ColorExpr></ColorExpr>
      </ScrollBkgColor>
      <ScrollButtonColor>
        <Col>
          <Red>192</Red>
          <Green>192</Green>
          <Blue>192</Blue>
          <Alpha>255</Alpha>
        </Col>
        <IsCalculated>false</IsCalculated>
        <ColorExpr></ColorExpr>
      </ScrollButtonColor>
      <ScrollStyle>SCROLL_SIX</ScrollStyle>
      <ScrollWidth>38</ScrollWidth>
      <AllowModify>true</AllowModify>
      <CopyImageIcon>false</CopyImageIcon>
      <PreserveScrollPosition>false</PreserveScrollPosition>
      <ShadowIntensity>SHADOW_NONE</ShadowIntensity>
      <OnActivateActionItems></OnActivateActionItems>
      <OnDeactivateActionItems></OnDeactivateActionItems>
      <Extension></Extension>
      <Background></Background>
      <MenuIcon>false</MenuIcon>
      <ExtendedProperties></ExtendedProperties>
      <ExtendedValues></ExtendedValues>
      <StateName></StateName>
    </Frame>
    <LegacyHelpModeThatHasNoEffectWhatSoEver>false</LegacyHelpModeThatHasNoEffectWhatSoEver>
    <TextAdjustHorizontal>1</TextAdjustHorizontal>
    <TextAdjustVertical>4</TextAdjustVertical>
    <TopMargin>10</TopMargin>
    <BottomMargin>10</BottomMargin>
    <LeftMargin>10</LeftMargin>
    <RightMargin>10</RightMargin>
    <TextColor>
      <Mode>COLORAREA_SOLID</Mode>
      <Luminosity>85</Luminosity>
      <FillDirection>COLORAREA_HORZ</FillDirection>
      <FillPattern>COLORAREA_PATTERN1</FillPattern>
      <PrimaryCol>
        <Col>
          <Red>54</Red>
          <Green>54</Green>
          <Blue>54</Blue>
          <Alpha>255</Alpha>
        </Col>
        <IsCalculated>false</IsCalculated>
        <ColorExpr></ColorExpr>
      </PrimaryCol>
      <SecondaryCol></SecondaryCol>
      <Alpha>255</Alpha>
    </TextColor>
    <BkgColor>
      <Mode>COLORAREA_SOLID</Mode>
      <Luminosity>85</Luminosity>
      <FillDirection>COLORAREA_HORZ</FillDirection>
      <FillPattern>COLORAREA_PATTERN1</FillPattern>
      <PrimaryCol>
        <Col>
          <Red>214</Red>
          <Green>231</Green>
          <Blue>248</Blue>
          <Alpha>255</Alpha>
        </Col>
        <IsCalculated>false</IsCalculated>
        <ColorExpr></ColorExpr>
      </PrimaryCol>
      <SecondaryCol></SecondaryCol>
      <Alpha>255</Alpha>
    </BkgColor>
    <BkgImageSettings></BkgImageSettings>
    <BkgMode>BKG_IMAGE</BkgMode>
    <Bmp enctype="base64">
        /9j/4AAQSkZJRgABAQAAAQABAAD/2wCEAAkGBxQHBhQUBxQWFRUXFx0bGBgYGR4aHxwdGh4dHBwi
        HBscICggIB4lIBsaIT0hJSksLi4uGCMzODMsNygtLysBCgoKDg0OGxAQGy8kICUtMjQtMDc0LC8v
        LCw0Ly8sLCwsLCw0LSwtLzQ0NC8sLCwsNDQsLywvLCwsLywsLCwsLP/AABEIAJ8BPgMBEQACEQED
        EQH/xAAcAAEAAgMBAQEAAAAAAAAAAAAABQYCBAcDAQj/xABLEAABAwIFAQQGBQkDCgcAAAABAAID
        BBEFBhIhMUEHE1FhFCIycYGRFVJzobEXIzU2QmJygrIWNMIzQ3Sjs8PR0tPwJVNUVZKTwf/EABoB
        AQADAQEBAAAAAAAAAAAAAAACAwQFAQb/xAA4EQACAgEDAQUGBgEEAQUAAAAAAQIDEQQSMSEFE0FR
        cRQyM4GxwSJhodHh8JE0U4LxUhUjJEJD/9oADAMBAAIRAxEAPwDuKAIAgCAIAgCAIAgCAIAgCAIA
        gCAIAgCAIAgCAIAgCAIAgCAIAgCAIAgCAIAgCAIAgCAIAgCAIAgCAIAgCAIAgCAIAgCAIAgCAIAg
        CAIAgCAIAgCAIAgCAIAgCAIAgCAIAgCAIAgCAIAgCAIAgCAIAgCAIAgCAIAgCAIAgCAIAgCAIAgC
        AIAgCAIAgCAIAgCAIAgCAIAgCAIAgCAIAgCAIAgCAIAgCAIAgCAIAgCAIAgCAIAgCAIAgCAIAgCA
        IAgCAIAgCAIAgCAIAgCAIDmedc5VWHZifDh7msbHp/ZDi4ua129x+9aw8FByeT6vsvsnTXaaNtib
        cs+OMdWvD0L3l6vdieBwyzABz2AkDi/W3kpI+d1tKo1E648JkivTMcmzpnurw7M0kVA5rGRkC2gO
        1bAkkkX69LbLs6XRVTqUpdWzk6nV2QtcY8Is+Y80S0mTKeopAGyTiPpcN1sLzYHni2/iuRfHu5uK
        8GfUdh6WvWW4s425x58fueXZ1mWfG5ZmYkQ7QGuDgA07kgg226KuLybu2+zqdMoTq6Zyscl3Uj58
        qPaTmGXL+EMdhtg979Ooi9hYnYHa+3XzW3RURtm1LhIyay6VUMxNTsxzPPmCOZuKEOMekh4AbcO1
        bEDbbT96nrtPCppw8SGi1E7U1LwLyuebggCAIAgCAIAgCAIAgCAIAgCAIAgCAIAgCAIAgCAIAgCA
        IAgCAICMxLL9Nik4fiELHuAtcje3nbn4rzCNdGu1FEdtc2ke9dWRYLhpfVERxRgDjYDgAAfAABWV
        1ynJRiupjttxmc36siMGzvR4xXCKjkOs+yHNLb28Cdr+Svs0dtcd0l0KK9VVY9sX1IXMuLYP9MuG
        MMbJM2wcQxx3HRxGziOOtuPJXUVarZ+B4RTdbpt/4+SbxzGKFuXmPxIsfTyW0ANJ1W40tAuLW8re
        SzR09lk3DHVcm2Gt9nxbCWPJo8Mm4rh9SJGZdDWEes9paWkgbXu7kC/jtfpdLdLZSsyRKfaUtY/x
        zcmvMw/KLQelaO9PNtWh2n5248+Fb7BfjODJ7ZTnGSw4jh8WLUmivY2RhsbHf3EHofMeKzQnKt5i
        8M0ShGaxJZRjhWEQ4PAW4ZG2NpNzbqfMncr2y2djzJ5PIVxgsRWDdVZMIAgCAIAgCAIAgCAIAgCA
        IAgCAIAgCAIAgCAIAgCAIAgCAIAgCAICr9o+FSYxlhzKAantc12nq4DkDz3v8Fr0Vsa7U5cGbV1y
        sqajyc2yVlerdmaB00EsbI3h7nSMLBZu+2oC5PFh4rqarUVd1JKSbZzNLp7O9Taawa2Zcq1cOPTa
        KeV4dI5zXMY54Ic4kbgGx34KnRqanWvxJdCN+mt7x4TZN5gyhVNyZRBkZe+Hve8Y31nDvXBwsBza
        1jbqfis9Oqq7+bz0eMfIvu01ncwWOqz+pj2eZWqfTZn1UT4WmCSMGRpaS54AFgd7Dm691upr2pJ5
        6p9DzR6exNtrHTBWf7JVvpXd+izar2voOn/5+xbzvZa/aqcbty/v5cmX2a3ONr/v58HfsNgNLh0T
        JNyxjWkjxaAP/wAXzc3uk2fQRWIpGyokiNzLUuosvVElMdL2RPc02BsQ0kbHZW0RUrIp8Nld0nGu
        TXkcxwPFsax6nc/DJQ5rXaSSIW72B6t8CF1batJU8TX1OXVPVWrMX9CS7nMH1x/qP+Cq3aHy+pbt
        1vn9C2ZMirmUkhzQ+7y71B6mzQObsHUk8/VWPUultd0unz+5r06tSfevqWJZjQEAQBAEAQBAEAQB
        AVfOucG5V7rXEZDJq/a02DbX6G59YbLXpdK789cYM2o1Kpx0zkssMnfQtc24BAO/nusrWHg0J5Rm
        vD0IAgCAIAgCAIAgCAIAgCAIAgOS9oGcqzDs0SQ4fJ3bIw2wDWnVqa1xJLgept4bLs6PSVTqUpLL
        ZydXqrIWuMXhInsx5inb2bxVEJ0Syhgc5u1tXJb4Xt8NWyzUUQ9pcH1SyaLrprTqa5ZR8k5jqmZn
        ga+aV7XvDHNe9zgQ7bgk2I5uPBdDVUV91J4SwYNLfZ3qTbeTui+fO6EBrYlOaXDpXxi5YxzgPMAk
        KUFukkyMniLZ+ff7T1npPeekzar39s2v/D7NvK1l9L7NVjG1Hz3tFu7O5nVs55hnw/LFPJREMfNp
        1OsDa7NRABuNz49F8xb+GTS8z7rsLSVaqx96spRzj/B87Ncfnxlk7cSdr0aS11gD62q4OkAfs3+K
        jF5NHbmhp0zhKpYznK9MdevqT2cf1Uq/sJP6StGm+NH1R81qPhS9GVXsX/QM/wBt/gatnafxF6fc
        y9nfDfqdCXNOga2I1Jo6F8jGOkLGk6G2ubc2v1t0UoR3SSzgjKW1NkblXM8WZ6Rz6IFpabOY61xf
        g7E7Hf5FW6jTypeJFdF8bVmJr1ub44MzNo4I3yyutcttZt9zqub7N9Y+SnHSydTtbwiMtRFWd2ll
        mebc1xZWjjNYx7+81W0W202ve5HivNPppX52vg9v1EasbvE08x58gwWtMMTHzSgXc1nDf4j4+QBU
        6dFOyO5vCIW6uNb24yz0yrninzHN3cQdHLa4Y+3rAc6SObeGxXmo0c6Vl9UKNXC14XRlirKtlDSu
        krHBjGi7nHgBZoxcniPJplJRWWUWbtPY+Q/RlLNMxp3f7PxsAfvst67OaX45JMwvXJ+7FtFhyvm2
        nzKw+hEte0XdG/ZwHiLbEeY8Re11mv0s6fe48zRTqYW+7z5GOac2xZalibVskeZdVtGnbTpG9yPr
        Be0aaVybT4F2ojVjPiReOdo0GGYt3FOx0rg4Ne4ODWg3sQDvcjr+Ktq0E5w3t4KrNbCM9iWSRznm
        KnwCOI4rE6UPLtNmtdYttv6xFueir01E7W9jwWai6FSW5ZJusrmUNA6aqOljW6nGxNh7hcrPGDlL
        auS6UlGO58FHl7UGzSkYTSTTAcnj7mh332XQXZzS/HJL+/IxPXp+5FslcsZ8gx6s7lzXwy72a+1j
        bkAjqPAgKm/RTqjuzlFlOrha9vDJTNGYY8tYeJaxr3NLwyzLXuQT1I29UqqiiV0tsS266NUd0iKx
        TP1PQ0kRibJJJLG2QRNALmteA4azcgbHpf5K2vRTk3lpJPGf2K56uEUsdW/A88s9oUGOVwhlY6GQ
        +yHEEOPgHDg+RC9v0M6o7k8ojTrIWS28MsdXiPotVocxxGh79QLbWZpvyb39YdFmjDKzk0ueHjBj
        hmLMxKRwga4aWMcbgf5wE259oW396TqcF1/P9DyFik+n5fqSCrLAgCAIAgCAIAgI/EMDpsTmDsQg
        jkcBYFzATbwuenl5qyF1kFiMmiuVUJPMkmaWcKmnw7Lb/paPXDYN7sDk39UDi1rXv0tdWaaNk7Vs
        eH5kL5QjW966FAyLi+H/ANooxDRuhkcdMbzKZQCfJ1rE8XF+V0dXVf3bbnlePTBg0ttPeJKOH4dc
        nXFxjrBAYTyCGFzpjZoBJJ8BuV6k28I8bwss4kcbwv6V1fR7+71Xv3p4+y9m37t7LvdzqdmO86+n
        3OL32n3+509fsdRzPjFJQ4G1+LtEkT9OhmkO1XGoWB2G29zay41WnnbNwXJ2fbHpsWRk15Y5PPJW
        L0eKUbxl9giDXDWzQGG54JtcG9jvfovb9NOlpS8T326Wre6Um2vM284/qpV/YSf0leab40fVFWo+
        FL0ZyjJOVp8ew976CpMAa/SWjVubA39Vw8bfBdjVamFUkpRz0OVpdPOyGYywWL8nNZ/7g7/Wf86z
        e31f7f0/Y1ex2/7jOgYNSOoMJiinfrcxgaXb+sQOd91zbJKU3JLGTfCLjFJnNMyRSZBzV6ThbQYZ
        w67OG6juWm3FjZw+I6Lq0OOqq7ufK/v8HMuzprd8eGTXZbgjmU763ErmacktJ50k3J/nO/uA8VRr
        7llVR4X9/Qu0VTSdkuWR/bb/AHel98n4MVnZfMvkV9pcRLzlvCW4ThjQBeRw1Sv6vkdu4k+8n3BY
        L7XZPPh4fkjdTWoRx4+Pqc87UqcYHmSmq6EaXuJc6213RlpufeHWPjZdLQN21Srlx+5z9au7sjZH
        k2e1/ETK+mp2O0sf67z03Ia0nyHrH5eCj2dXjdPHVEtfPO2GeS1YdmHDsMomRUVRC1jBYAOHzPiT
        zfqsc6NROTlKLya4XUwioxksFCzBXwUGfqepy9IxzXuaZBGdrl2l/H1mn53K6NMJz08oWLjj7GC2
        cI3xnW+eSQ7aAXVdGGbE95b33jVfZnE/l9yfaKy4YL9g2AwYRQtjpmN2HrOIBc89XOPUlc226dks
        t/wdCuqMI4SKL22/3el98n4MXQ7L5l8jD2l7sTosrGS4cRWW7sss/VxpI9a/la65ibUsx5Og0nHr
        wVRue6DDyIcJa+QDYNgi228OL+8XWz2K+X4p9PVmX2umP4Y9fRFRxnFI8T7RqOWhY+Ml0QeHs0Ov
        3hG46+qQL+XkttVcoaacZPPP5+BjtsUtTBx6cfUs3bJ+q8f27f6JFl7M+K/T7o0do/CXr9mTOQcN
        ZQZXgMAGqSNj3u6kuaCLnwANgOgCz6uxytkn4M0aaCjWseRS+1albQ5kpJ6UBr3m7iNrmNzdJPn6
        1r+QW/s+TlVKD4/cxa6KjZGa5OpS07ZnXlAJ0ub/ACutqHx0j5LkKTXB1GkzGmo46VxNM0N1c267
        ud+LnH4r2U5S5Z4oqPB7qJIIAgCAIAgCAIAgIDPGBnMGX3RQODXghzS7i7ehPQWJ3WjS3KqxSZRq
        au9rcUc/yZkaZmYI5Kp8WiJweQyQPJI4Fm8C9tyulqdbB1uKT6nP02jkrFJtdDrE1XHA+072NJ4B
        cAfkVx1FvhHWckuT1kkETCZSABySbD5rxJvg9zg15tGJ0L2RPDmva5pLSDbULdOu6kswkm0ReJJo
        4x+Tqp+ke67yn5tfvBe3jo9q9ull3Pb69u7D/wAHG9gnuxlHSM15R+nMAighk0Oh06XEXBs3TuB4
        jdcvT6rurHNrk6V+n72CjngwyFlA5WjlM8gkfJp9kWADb253J9Y/cvdXqu/awsJEdLpu5T65ySmc
        f1Uq/sJP6SqdN8aPqi3UfCl6MqvYv+gZ/tv8DVs7T+IvT7mXs74b9ToS5p0AgOT46X9oGcPR6F1q
        eAOu/kX4LvO7rNHkCfFdirGkp3y95nKtzqrdi4RKdmWMvpKiTDsW2kiJ7u/UDdzR429oeIJ6BVa6
        pSSuhw+S3R2uLdM+VwavbbvT0vvk/Bil2XzL5EO0uInQMExBuKYVHLF+00XHUOGzgfMG4+C51sHC
        bizoVzU4po5x2vSDEcapKam3k3Fh0MpY1o9/q/eF0+zlshKb4/Y5uve6cILn9z72u0Xo9fSTSN1R
        gaHD+E6rfEF3yKdnTzGcVzye6+OJRk+C2U2S8Nqqdr6enY5rgC0hzrEHcH2ljlq9RF4cjWtNQ1lR
        Iqvw7CcKzBBTyU/52Qgt06naTcBur1ri5v06b7K2E9TZW57uiKpQ08LFDb1ZGdsf6Qofe/8AGNXd
        m+7P5fcq1/vQ/vkdQXJOmcx7bf7vS++T8GLq9l8y+Rze0vdib3a5Vvp8rRMhJDZHgPt1AaXAfEgH
        +VQ7Oina2/BE9fJqpJeJZcoYTDhOBxDDwPWY1znjl5IBuT1528AsmptnZY93/RporjCCUSh5wrWV
        falSNgIPdvhY63R3eFxHwDh8bro6aDjpJN+Ofoc/UyT1UceGPqTfbJ+q8f27f6JFR2Z8V+n3Rd2j
        8Jev2ZZso/qpSf6PF/Q1ZNR8afq/qa6Phx9EUXtk/SFF/P8AjGuh2b7s/l9zD2hzA6guSdMIAgCA
        IAgCAIAgCA5D2jT1DM0vBdK1lm91YuAtpF7W5OrV5/cq5cn23YkKHpE8Jvru4zy8Zz+WCczhJUHs
        ujNRr1kR97fnSfrdedN/vXQ7Ox3yyfE9ubVOxU+7u8PL9jn2Q3Pbm+m9EvcyAG31f27+Wm67Grx3
        Ms+R89pHLvo4NTNJe7MlT6ZfX3r76ubXOn4Wtbysp6fHdR2+RHUZ72WfMncySTOyDh3pBfoJlvfj
        Zw7q/wDJqt5LPQoe0WY56fz/ACX3Ofs8M/n/AAOzB0rcWn+j9X92k441C2jyvq4+Pmmv27I7vNfy
        e6HduljyKhqPeXudV73639/N7rb0wYsvP5n6XwwuOGxek31923VfnVYXv53Xys8bnjg+mjnasmyo
        kjTxmh+k8JlhDtPeMczVa9tQte1xf5qdU9k1LyZCyO+Lj5nO2dk74x+brbe6Ij/eLpvtOL5h+v8A
        Bz12c1xMy/JXJ/68/wD1n/qrz/1KP/h+v8HvsEv/ADf9+ZP4LlKfCMDqIIay5l9l5jN2XFnWHebk
        gC24sRfdZ7dVCyyM3Dj8+f0NFenlCDju5N/JuV2ZXw4sY7W9zrvfp03t7Itc2AHnySeqr1Ood8s8
        Inp6FTHCNTM2TfpfGIqnD5u4mjtd2jXq0+zcam8bjrcG3RTo1fdwdcllMhdpt81NPDRW+2y/odLr
        5vJe3uYtXZfvS+Rm7R4iTeM5PmfWOmy1VOpjJvIy50Od1cLcE+4/BZ69VDG22O7HHmX2aaWd1csZ
        GVMiDCcRNRispnn5BN7NJ2JuSS53mePDqmo1veR2QWEKNJslvk8ss+M4VFjWHuhr23Y74EEcEHoQ
        stVkq5bo8mmyuNkdsijwZIr8JBZgdfpiJNg4EWv4CzhfzFrre9ZRZ1sh1MUdLdDpCfQmsrZKZg1Y
        Z66R1RUH/OO6X2NgSTe22onji26ov1bsjsisR8i6nSquW+Ty/MyznlE5nqIHNm7rutW2jVq1Fp+s
        Lez58rzTaruVJYzk91Gn71p5xgtKyGkq2ecpHNUcQbKIu7LuWar6rfvC3H3rXpdV3DfTOTNqdP3y
        SzjBK49gceO4OYKy9trOHLXDgj/vglU03SqnviWW1RshtkU2gyRiFCzuafENEH7urUB+60+z8HLd
        PWUS/E6+v9/vBkhpbo/hU+hnjfZuXPp3ZekETohu597lwdqD9QHtXJ6eHFl5Vr/eVizn+4Fmh911
        vDX9yT+assvzFgEUEswa9jmuc/Tq1FrS07XFrl11n0+oVNjmkX30O2Ci2TGD0X0bhMMJdq7uNrNV
        rX0tAvbe17cKiye+bl5svhHbFR8iBzplA5nqIHNmEfdatizVfUWn6wt7P3rRptV3KksZyZ9Rp++a
        ecYLUshqCAIAgCAIAgCAIAgCA1cUq2UGHSSVv+Ta0l217jwt1vxbzTOOpbTTK6xVw5ZVso5joa7E
        zHhlMKeRwNj3bG6gNyLs69bHwXrunPpJtm/VdhT0dfe/hx44/wCkWeqwmCsm1VkMT3Dhz2NcfmRd
        SjbOKxFtHIlXCTy0maObMVp8FwYuxZmuMkNEekO1E7gWdtwCd/BWaeqdk8QeH5kL7IVwzPg0Mj4/
        SYxHI3BoRAW2LmaGtvfg+pseLKzVUW1tObyV6a6uaagsE59EU/pfe9xF3l76+7bqv46rXuqO9njb
        uePUv7qGd2Fk1sx4/Hl6iElYHG7tLWttcnnqQOAVU3g36HQ2auzZDCwsts8ssZmizHE80gc1zCNT
        XWvvexFiQQbH5Inks1/Z1ujaU2mnw0Ta9OeEAQBAEAQFN7RsrTZnhhGHmMaC++ske0G2tZp8Ct2i
        1MKW92epj1enldjb4FxaLNF1hNh9QBAEAQBAEAQBAEAQBAEAQBAEAQBAEAQBAEAQBAEBp4xhzcWw
        uSGYkB7bXHI8D8CvGsl+mvdFsbY8plXyrkP6DxUTTzd4WghoDNO7hYk+sb7E7ea8UcHX7Q7b9qp7
        qMMZ565+yLopHBIPOGXRmbCe6e8sIcHtda9iARuLi4sT1WjTXume7GSjUUK6G1mhkfJgys6Rz5e9
        fJYbN0gAXPFzvc8qzVavv8LGMENNpVTnrnJa1jNRBZvy4MyYe1mvu3Ndqa62ocEEEXHQ+K8aydHs
        3XvR2OeMprDXB4ZNyqMtRyapO8fJa506QA29gBc+J3uiWCfafab1rj+HCXz5/wAFkXpywgCAIAgC
        AIAgCAIAgCAIAgCAIAgCAIAgCAIAgCAIAgCAIAgCAIAgCAIAgCAIAgCAIAgKFnZkuYsY9Ewp5aae
        MzvI/wDMt+abfoevudfoujpXGqHeTXLx8vFmHUKVs9kXx1+fgi05YxYY3gUUw2Lm2ePB42cPmD8F
        kvq7uxx/uDVTZ3kFI98VxNmFQNfVX0ue1lwL2LzpBPgLkb+ahXW5vCJTmorLPOpxqKmxmKmlJ72V
        pc0W2s253PnY/IqUapODmuERdkVNQfLPKfMMFPJUCocWimDe9cR6t3i4APV1rbD6w8V6qJvbj/7c
        Hjuit2fDk16LNUdRWMjqIp4DJtGZo9DXnmwNzY26OsVKWmkk2mnjnD4IxvTeGms8Z8RV5qhp8SfA
        xk0krHNBZGzUbPAOrY+yARcm3PVI6aTip5ST8w74qTj1bRr4U/Tniv1nYRQHfgbPupWL/wBiHq/s
        eQ+NL0RHZjzTFiOWKkUzJgx0TxHM5hbG8gH2XefS4FzsN9lbTppQtjlrOVleKK7b4yrlhPHn4Mt2
        Gfo2L7Nv4BYp+8zVH3URddmiOmrXx08U87o/8p3MesMvvZxuN7b2FyroaeUoqTaWeMvkrlek8JN+
        ngQmfcfZVZIc7De8e2Zu0jGnS0B7A4SH9gm5bY8m4WjSUON6UsdPD5eHmZ9XcnQ3Hx/vUsmW44os
        HYMOhfBGL2jkaWuG5vcO33Nz8VkvcnNuTy/M1Vbdi2rCNLDsQio4a6UPmeIpnmQP30lrQS2MfVtw
        PElWThKThHC6rp/JCM4xUnl9H1/gxOcoA+MuZMIpC0NmMdo7u4BdfztcAjnfYp7JPr1WV4Z6nntM
        enR4fj4G1iWYmUVcYYYpp5A0Oc2FgdpBvbUSQBex2vfyUYUOUdzaS/MnO5Re1Jt/kaON4xBiOUny
        mSaOMPa1xj9SVjhI0aSDuDewI8CVOqqcLlHCb/Ph9CFlkJVN5aX6kji+PMwyqZFoklleCRHE3U7S
        OXG5ADelyVXXS5pyykl4snO1QeMZfkjVfj8WK0NUyk1ao4SXBzdNtTXbEHcOBaQQRsQp9zKEot+L
        I97Gakl4IiMAzXFhuWqQVTJizu2NfOGExtdYD1nnz2JAIB25V12mlO2WGs5fTxKq9RGNccp48/A9
        sxZkfQZqpoo2VBjHeF7WRF3e+oC3QeXBuo3tweeFGnTqVMpNrPTHXjr4+QtvcbYxWcdfDkuDTdqx
        Gw+oAgCAIAgCAIAgCAIAgCAIAgCAIAgNfEKxuHUL5ak2axpc73AX+alCDnJRXiRlJRTbKLlnCsQl
        pnVVPNDE6qPeua+MvcAfYF7jYNtYdLroX2UJqtpvb05/yY6a7WnNNLd1NrKrZcvZmkpcUc13pIM8
        bmjS3Xf840A8G1jbwHmoajbbUrIL3ej9PAlSpV2OEvHqvXxLLmXDvpbAJoRy9h0/xDdp+DgCstFn
        d2KRothvg4lKgqjjGDy4kQdUT4HN2/ZpwDNbyJknHwW9x7uao88/rx9EZFJzg7fLH6c/czq6Z02T
        jVFpcJKsVUjQLkxB/q7dQIww28l5GSV3d+Udq9cfuetPut/m8/LP7EhmrFYccgpocHkZNK+eN7dB
        DixrDqc91vZAFxvY7qqiqdblKawkn8/yJ3WRmlGLy8r5G9l4D+2WJnrqg/2Shd8Gv5/UlV8Wz5fQ
        0aiB1Vj+LspvbdSxtb73RyAfepqSjXU3xuf1RFpudiXl+5HVmN083Zh3UTmulFMGGIe210bQHlze
        QGkF1z4eYVsaZrVbmumefDqVuyD0+3xxwXzC/wBGRfZt/pC50/eZtj7qKrljE4cDlrIcYkZFIKmS
        T84Q3Wx9i1zSedttuLLZfXO1QlBZWEvRrwM1U41uUZPDz/khKxh/JnXSEEMmqHSxAi35t0zNOx4v
        Yn4rRF//ACoR8UsP1wzPNP2ab8G8r0yjpzfZXJOmUJh/8Bxv7Wf/AGTV0f8A9KfRfUxP3Lfn9DYz
        Lt2axfw039UahR/qX/y+5K34C+X2MsabC7Msvo1Y+hqBGzUXaNErd9JDXmztO4vtbdKt3dLMN0c/
        Nf4PLNvePEtrx8mROKYk/EezmpdVljtNQ1glY3S2UCWP1wPMki42uFdXWoamKXlx5dH0K5zcqJZ8
        +fPryTdTVswntBc/E3NjZLTNbG95s27HkubqOwO4KojF2afEOuH1Xy5LnJQvzLpldDRoKllZjeLv
        pN2OgjId0d+beNQ8QbbHra/VTnFxrqT839UQg052NeSPtcB+R0f6Kz/Ckf8AW/8AI9f+m+Rt5hqm
        UeacMfVvaxgbPdziABeNvJOyjTFyqsUVl9PqLZKNtbf5lwBuNlhNh9QBAEAQBAEAQBAEAQBAEAQB
        AEAQBAYvYJG2eAR4HdM4B9AsNkB8cwOcC4AkcG3HuXuRgyXgMBGGssALeFtt+dl7ljBk0aW2bsF4
        Dxgo46Z5NOxjSeS1oF/fblScpPlniilwj1DA1xLQLnk+PvUcnoDAHEgC55KZB5ikjEjnBjLu9o6R
        c+89fipbnxk82ryPUCw2UT08aijjqXA1LGPI41NBt7r8KSlJcM8cU+Uer2B7bPAI8Co5PTJAYd02
        xFhvztz7/Fe5Z5g+ujDmWcAR4W228kyz3B5VVHHVgCrjY+3Gpodb3XXsZSjw8Hjinyj0MTTHpIGn
        wttt5LzL5GCFx3Cp6ura+gkiI02dDOwyRkg3DgAQWvFyL9R7lfVZCKxJP1XR+hVZXJvKfyfVGeA4
        M6hnmlxB7ZJp9OvS3SwNYLNa1pJNgCdyd7ry21SSjFYS/wAntde1uT5ZLmMGPSQLeFtvkqcvkswY
        VFKyqYBUsa8A3Ac0Gx8rr1SceGHFPlHsonoQBAEAQBAEAQBAEAQBAEAQBAEAQBAEAQBAEAQBAEAQ
        BAEAQBAEAQBAEAQBAEAQBAEAQBAEAQBAEAQBAEAQBAEAQBAEAQBAEAQBAEAQBAEAQBAEAQBAEAQB
        AEAQBAEAQBAEAQBAEAQBAEAQBAEAQBAEAQBAEAQBAEAQBAEAQBAEAQBAEAQBAEAQBAEAQBAEAQBA
        EAQBAEAQBAEAQBAEAQBAEAQBAEAQBAEAQBAEAQBAEAQBAEAQBAEAQBAEAQBAEAQBAEAQBAEAQBAE
        AQBAf//Z
    </Bmp>
    <BkgAlpha>255</BkgAlpha>
    <Text></Text>
    <ImageRepresentation></ImageRepresentation>
    <AllowVerticalScrollBar>false</AllowVerticalScrollBar>
    <AllowHorizontalScrollBar>false</AllowHorizontalScrollBar>
    <ActionItems></ActionItems>
  </Layout>
  <PrintSettings></PrintSettings>
  <UserSized>true</UserSized>
</TextObjectProperties>
